topsis/__init__.py
topsis/__main__.py
topsis_dev_102117160-1.0.2.dist-info/METADATA
topsis_dev_102117160-1.0.2.dist-info/WHEEL
topsis_dev_102117160-1.0.2.dist-info/entry_points.txt
topsis_dev_102117160-1.0.2.dist-info/top_level.txt
topsis_dev_102117160-1.0.2.dist-info/RECORD
